<?xml version="1.0" encoding="UTF-8"?>
<?xml-stylesheet href="CoreNLP-to-HTML.xsl" type="text/xsl"?>
<root>
  <document>
    <sentences>
      <sentence id="1">
        <tokens>
          <token id="1">
            <word>But</word>
            <lemma>but</lemma>
            <CharacterOffsetBegin>0</CharacterOffsetBegin>
            <CharacterOffsetEnd>3</CharacterOffsetEnd>
            <POS>CC</POS>
            <NER>O</NER>
            <Speaker>PER0</Speaker>
          </token>
          <token id="2">
            <word>yesterday</word>
            <lemma>yesterday</lemma>
            <CharacterOffsetBegin>4</CharacterOffsetBegin>
            <CharacterOffsetEnd>13</CharacterOffsetEnd>
            <POS>NN</POS>
            <NER>DATE</NER>
            <NormalizedNER>OFFSET P-1D</NormalizedNER>
            <Speaker>PER0</Speaker>
            <Timex tid="t1" type="DATE"/>
          </token>
          <token id="3">
            <word>or</word>
            <lemma>or</lemma>
            <CharacterOffsetBegin>14</CharacterOffsetBegin>
            <CharacterOffsetEnd>16</CharacterOffsetEnd>
            <POS>CC</POS>
            <NER>O</NER>
            <Speaker>PER0</Speaker>
          </token>
          <token id="4">
            <word>two</word>
            <lemma>two</lemma>
            <CharacterOffsetBegin>17</CharacterOffsetBegin>
            <CharacterOffsetEnd>20</CharacterOffsetEnd>
            <POS>CD</POS>
            <NER>DATE</NER>
            <NormalizedNER>OFFSET P-2D</NormalizedNER>
            <Speaker>PER0</Speaker>
            <Timex tid="t2" type="DATE"/>
          </token>
          <token id="5">
            <word>days</word>
            <lemma>day</lemma>
            <CharacterOffsetBegin>21</CharacterOffsetBegin>
            <CharacterOffsetEnd>25</CharacterOffsetEnd>
            <POS>NNS</POS>
            <NER>DATE</NER>
            <NormalizedNER>OFFSET P-2D</NormalizedNER>
            <Speaker>PER0</Speaker>
            <Timex tid="t2" type="DATE"/>
          </token>
          <token id="6">
            <word>ago</word>
            <lemma>ago</lemma>
            <CharacterOffsetBegin>26</CharacterOffsetBegin>
            <CharacterOffsetEnd>29</CharacterOffsetEnd>
            <POS>RB</POS>
            <NER>DATE</NER>
            <NormalizedNER>OFFSET P-2D</NormalizedNER>
            <Speaker>PER0</Speaker>
            <Timex tid="t2" type="DATE"/>
          </token>
          <token id="7">
            <word>,</word>
            <lemma>,</lemma>
            <CharacterOffsetBegin>29</CharacterOffsetBegin>
            <CharacterOffsetEnd>30</CharacterOffsetEnd>
            <POS>,</POS>
            <NER>O</NER>
            <Speaker>PER0</Speaker>
          </token>
          <token id="8">
            <word>they</word>
            <lemma>they</lemma>
            <CharacterOffsetBegin>31</CharacterOffsetBegin>
            <CharacterOffsetEnd>35</CharacterOffsetEnd>
            <POS>PRP</POS>
            <NER>O</NER>
            <Speaker>PER0</Speaker>
          </token>
          <token id="9">
            <word>had</word>
            <lemma>have</lemma>
            <CharacterOffsetBegin>36</CharacterOffsetBegin>
            <CharacterOffsetEnd>39</CharacterOffsetEnd>
            <POS>VBD</POS>
            <NER>O</NER>
            <Speaker>PER0</Speaker>
          </token>
          <token id="10">
            <word>story</word>
            <lemma>story</lemma>
            <CharacterOffsetBegin>40</CharacterOffsetBegin>
            <CharacterOffsetEnd>45</CharacterOffsetEnd>
            <POS>NN</POS>
            <NER>O</NER>
            <Speaker>PER0</Speaker>
          </token>
          <token id="11">
            <word>about</word>
            <lemma>about</lemma>
            <CharacterOffsetBegin>46</CharacterOffsetBegin>
            <CharacterOffsetEnd>51</CharacterOffsetEnd>
            <POS>IN</POS>
            <NER>O</NER>
            <Speaker>PER0</Speaker>
          </token>
          <token id="12">
            <word>me</word>
            <lemma>I</lemma>
            <CharacterOffsetBegin>52</CharacterOffsetBegin>
            <CharacterOffsetEnd>54</CharacterOffsetEnd>
            <POS>PRP</POS>
            <NER>O</NER>
            <Speaker>PER0</Speaker>
          </token>
          <token id="13">
            <word>and</word>
            <lemma>and</lemma>
            <CharacterOffsetBegin>55</CharacterOffsetBegin>
            <CharacterOffsetEnd>58</CharacterOffsetEnd>
            <POS>CC</POS>
            <NER>O</NER>
            <Speaker>PER0</Speaker>
          </token>
          <token id="14">
            <word>they</word>
            <lemma>they</lemma>
            <CharacterOffsetBegin>59</CharacterOffsetBegin>
            <CharacterOffsetEnd>63</CharacterOffsetEnd>
            <POS>PRP</POS>
            <NER>O</NER>
            <Speaker>PER0</Speaker>
          </token>
          <token id="15">
            <word>had</word>
            <lemma>have</lemma>
            <CharacterOffsetBegin>64</CharacterOffsetBegin>
            <CharacterOffsetEnd>67</CharacterOffsetEnd>
            <POS>VBD</POS>
            <NER>O</NER>
            <Speaker>PER0</Speaker>
          </token>
          <token id="16">
            <word>some</word>
            <lemma>some</lemma>
            <CharacterOffsetBegin>68</CharacterOffsetBegin>
            <CharacterOffsetEnd>72</CharacterOffsetEnd>
            <POS>DT</POS>
            <NER>O</NER>
            <Speaker>PER0</Speaker>
          </token>
          <token id="17">
            <word>low</word>
            <lemma>low</lemma>
            <CharacterOffsetBegin>73</CharacterOffsetBegin>
            <CharacterOffsetEnd>76</CharacterOffsetEnd>
            <POS>JJ</POS>
            <NER>O</NER>
            <Speaker>PER0</Speaker>
          </token>
          <token id="18">
            <word>level</word>
            <lemma>level</lemma>
            <CharacterOffsetBegin>77</CharacterOffsetBegin>
            <CharacterOffsetEnd>82</CharacterOffsetEnd>
            <POS>NN</POS>
            <NER>O</NER>
            <Speaker>PER0</Speaker>
          </token>
          <token id="19">
            <word>Hispanic</word>
            <lemma>hispanic</lemma>
            <CharacterOffsetBegin>83</CharacterOffsetBegin>
            <CharacterOffsetEnd>91</CharacterOffsetEnd>
            <POS>JJ</POS>
            <NER>MISC</NER>
            <Speaker>PER0</Speaker>
          </token>
          <token id="20">
            <word>commentator</word>
            <lemma>commentator</lemma>
            <CharacterOffsetBegin>92</CharacterOffsetBegin>
            <CharacterOffsetEnd>103</CharacterOffsetEnd>
            <POS>NN</POS>
            <NER>O</NER>
            <Speaker>PER0</Speaker>
          </token>
          <token id="21">
            <word>.</word>
            <lemma>.</lemma>
            <CharacterOffsetBegin>103</CharacterOffsetBegin>
            <CharacterOffsetEnd>104</CharacterOffsetEnd>
            <POS>.</POS>
            <NER>O</NER>
            <Speaker>PER0</Speaker>
          </token>
        </tokens>
        <parse>(ROOT (S (CC But) (S (NP (NP-TMP (NN yesterday)) (CC or) (ADVP (NP (CD two) (NNS days)) (RB ago))) (, ,) (NP (PRP they)) (VP (VBD had) (NP (NP (NN story)) (PP (IN about) (NP (PRP me)))))) (CC and) (S (NP (PRP they)) (VP (VBD had) (NP (DT some) (JJ low) (NN level) (JJ Hispanic) (NN commentator)))) (. .))) </parse>
        <dependencies type="basic-dependencies">
          <dep type="root">
            <governor idx="0">ROOT</governor>
            <dependent idx="9">had</dependent>
          </dep>
          <dep type="cc">
            <governor idx="9">had</governor>
            <dependent idx="1">But</dependent>
          </dep>
          <dep type="nsubj">
            <governor idx="9">had</governor>
            <dependent idx="2">yesterday</dependent>
          </dep>
          <dep type="cc">
            <governor idx="2">yesterday</governor>
            <dependent idx="3">or</dependent>
          </dep>
          <dep type="num">
            <governor idx="5">days</governor>
            <dependent idx="4">two</dependent>
          </dep>
          <dep type="npadvmod">
            <governor idx="6">ago</governor>
            <dependent idx="5">days</dependent>
          </dep>
          <dep type="advmod">
            <governor idx="2">yesterday</governor>
            <dependent idx="6">ago</dependent>
          </dep>
          <dep type="nsubj">
            <governor idx="9">had</governor>
            <dependent idx="8">they</dependent>
          </dep>
          <dep type="dobj">
            <governor idx="9">had</governor>
            <dependent idx="10">story</dependent>
          </dep>
          <dep type="prep">
            <governor idx="10">story</governor>
            <dependent idx="11">about</dependent>
          </dep>
          <dep type="pobj">
            <governor idx="11">about</governor>
            <dependent idx="12">me</dependent>
          </dep>
          <dep type="cc">
            <governor idx="9">had</governor>
            <dependent idx="13">and</dependent>
          </dep>
          <dep type="nsubj">
            <governor idx="15">had</governor>
            <dependent idx="14">they</dependent>
          </dep>
          <dep type="conj">
            <governor idx="9">had</governor>
            <dependent idx="15">had</dependent>
          </dep>
          <dep type="det">
            <governor idx="20">commentator</governor>
            <dependent idx="16">some</dependent>
          </dep>
          <dep type="amod">
            <governor idx="20">commentator</governor>
            <dependent idx="17">low</dependent>
          </dep>
          <dep type="nn">
            <governor idx="20">commentator</governor>
            <dependent idx="18">level</dependent>
          </dep>
          <dep type="amod">
            <governor idx="20">commentator</governor>
            <dependent idx="19">Hispanic</dependent>
          </dep>
          <dep type="dobj">
            <governor idx="15">had</governor>
            <dependent idx="20">commentator</dependent>
          </dep>
        </dependencies>
        <dependencies type="collapsed-dependencies">
          <dep type="root">
            <governor idx="0">ROOT</governor>
            <dependent idx="9">had</dependent>
          </dep>
          <dep type="nsubj">
            <governor idx="9">had</governor>
            <dependent idx="2">yesterday</dependent>
          </dep>
          <dep type="cc">
            <governor idx="2">yesterday</governor>
            <dependent idx="3">or</dependent>
          </dep>
          <dep type="num">
            <governor idx="5">days</governor>
            <dependent idx="4">two</dependent>
          </dep>
          <dep type="npadvmod">
            <governor idx="6">ago</governor>
            <dependent idx="5">days</dependent>
          </dep>
          <dep type="advmod">
            <governor idx="2">yesterday</governor>
            <dependent idx="6">ago</dependent>
          </dep>
          <dep type="nsubj">
            <governor idx="9">had</governor>
            <dependent idx="8">they</dependent>
          </dep>
          <dep type="dobj">
            <governor idx="9">had</governor>
            <dependent idx="10">story</dependent>
          </dep>
          <dep type="prep_about">
            <governor idx="10">story</governor>
            <dependent idx="12">me</dependent>
          </dep>
          <dep type="nsubj">
            <governor idx="15">had</governor>
            <dependent idx="14">they</dependent>
          </dep>
          <dep type="conj_and">
            <governor idx="9">had</governor>
            <dependent idx="15">had</dependent>
          </dep>
          <dep type="det">
            <governor idx="20">commentator</governor>
            <dependent idx="16">some</dependent>
          </dep>
          <dep type="amod">
            <governor idx="20">commentator</governor>
            <dependent idx="17">low</dependent>
          </dep>
          <dep type="nn">
            <governor idx="20">commentator</governor>
            <dependent idx="18">level</dependent>
          </dep>
          <dep type="amod">
            <governor idx="20">commentator</governor>
            <dependent idx="19">Hispanic</dependent>
          </dep>
          <dep type="dobj">
            <governor idx="15">had</governor>
            <dependent idx="20">commentator</dependent>
          </dep>
        </dependencies>
        <dependencies type="collapsed-ccprocessed-dependencies">
          <dep type="root">
            <governor idx="0">ROOT</governor>
            <dependent idx="9">had</dependent>
          </dep>
          <dep type="nsubj">
            <governor idx="9">had</governor>
            <dependent idx="2">yesterday</dependent>
          </dep>
          <dep type="cc">
            <governor idx="2">yesterday</governor>
            <dependent idx="3">or</dependent>
          </dep>
          <dep type="num">
            <governor idx="5">days</governor>
            <dependent idx="4">two</dependent>
          </dep>
          <dep type="npadvmod">
            <governor idx="6">ago</governor>
            <dependent idx="5">days</dependent>
          </dep>
          <dep type="advmod">
            <governor idx="2">yesterday</governor>
            <dependent idx="6">ago</dependent>
          </dep>
          <dep type="nsubj">
            <governor idx="9">had</governor>
            <dependent idx="8">they</dependent>
          </dep>
          <dep type="dobj">
            <governor idx="9">had</governor>
            <dependent idx="10">story</dependent>
          </dep>
          <dep type="prep_about">
            <governor idx="10">story</governor>
            <dependent idx="12">me</dependent>
          </dep>
          <dep type="nsubj">
            <governor idx="15">had</governor>
            <dependent idx="14">they</dependent>
          </dep>
          <dep type="conj_and">
            <governor idx="9">had</governor>
            <dependent idx="15">had</dependent>
          </dep>
          <dep type="det">
            <governor idx="20">commentator</governor>
            <dependent idx="16">some</dependent>
          </dep>
          <dep type="amod">
            <governor idx="20">commentator</governor>
            <dependent idx="17">low</dependent>
          </dep>
          <dep type="nn">
            <governor idx="20">commentator</governor>
            <dependent idx="18">level</dependent>
          </dep>
          <dep type="amod">
            <governor idx="20">commentator</governor>
            <dependent idx="19">Hispanic</dependent>
          </dep>
          <dep type="dobj">
            <governor idx="15">had</governor>
            <dependent idx="20">commentator</dependent>
          </dep>
        </dependencies>
      </sentence>
      <sentence id="2">
        <tokens>
          <token id="1">
            <word>Low</word>
            <lemma>low</lemma>
            <CharacterOffsetBegin>105</CharacterOffsetBegin>
            <CharacterOffsetEnd>108</CharacterOffsetEnd>
            <POS>JJ</POS>
            <NER>O</NER>
            <Speaker>PER0</Speaker>
          </token>
          <token id="2">
            <word>level</word>
            <lemma>level</lemma>
            <CharacterOffsetBegin>109</CharacterOffsetBegin>
            <CharacterOffsetEnd>114</CharacterOffsetEnd>
            <POS>NN</POS>
            <NER>O</NER>
            <Speaker>PER0</Speaker>
          </token>
          <token id="3">
            <word>guy</word>
            <lemma>guy</lemma>
            <CharacterOffsetBegin>115</CharacterOffsetBegin>
            <CharacterOffsetEnd>118</CharacterOffsetEnd>
            <POS>NN</POS>
            <NER>O</NER>
            <Speaker>PER0</Speaker>
          </token>
          <token id="4">
            <word>.</word>
            <lemma>.</lemma>
            <CharacterOffsetBegin>118</CharacterOffsetBegin>
            <CharacterOffsetEnd>119</CharacterOffsetEnd>
            <POS>.</POS>
            <NER>O</NER>
            <Speaker>PER0</Speaker>
          </token>
        </tokens>
        <parse>(ROOT (NP (NP (JJ Low) (NN level)) (NP (NN guy)) (. .))) </parse>
        <dependencies type="basic-dependencies">
          <dep type="root">
            <governor idx="0">ROOT</governor>
            <dependent idx="2">level</dependent>
          </dep>
          <dep type="amod">
            <governor idx="2">level</governor>
            <dependent idx="1">Low</dependent>
          </dep>
          <dep type="dep">
            <governor idx="2">level</governor>
            <dependent idx="3">guy</dependent>
          </dep>
        </dependencies>
        <dependencies type="collapsed-dependencies">
          <dep type="root">
            <governor idx="0">ROOT</governor>
            <dependent idx="2">level</dependent>
          </dep>
          <dep type="amod">
            <governor idx="2">level</governor>
            <dependent idx="1">Low</dependent>
          </dep>
          <dep type="dep">
            <governor idx="2">level</governor>
            <dependent idx="3">guy</dependent>
          </dep>
        </dependencies>
        <dependencies type="collapsed-ccprocessed-dependencies">
          <dep type="root">
            <governor idx="0">ROOT</governor>
            <dependent idx="2">level</dependent>
          </dep>
          <dep type="amod">
            <governor idx="2">level</governor>
            <dependent idx="1">Low</dependent>
          </dep>
          <dep type="dep">
            <governor idx="2">level</governor>
            <dependent idx="3">guy</dependent>
          </dep>
        </dependencies>
      </sentence>
      <sentence id="3">
        <tokens>
          <token id="1">
            <word>This</word>
            <lemma>this</lemma>
            <CharacterOffsetBegin>120</CharacterOffsetBegin>
            <CharacterOffsetEnd>124</CharacterOffsetEnd>
            <POS>DT</POS>
            <NER>O</NER>
            <Speaker>PER0</Speaker>
          </token>
          <token id="2">
            <word>one</word>
            <lemma>one</lemma>
            <CharacterOffsetBegin>125</CharacterOffsetBegin>
            <CharacterOffsetEnd>128</CharacterOffsetEnd>
            <POS>NN</POS>
            <NER>NUMBER</NER>
            <NormalizedNER>1.0</NormalizedNER>
            <Speaker>PER0</Speaker>
          </token>
          <token id="3">
            <word>did</word>
            <lemma>do</lemma>
            <CharacterOffsetBegin>129</CharacterOffsetBegin>
            <CharacterOffsetEnd>132</CharacterOffsetEnd>
            <POS>VBD</POS>
            <NER>O</NER>
            <Speaker>PER0</Speaker>
          </token>
          <token id="4">
            <word>n't</word>
            <lemma>not</lemma>
            <CharacterOffsetBegin>132</CharacterOffsetBegin>
            <CharacterOffsetEnd>135</CharacterOffsetEnd>
            <POS>RB</POS>
            <NER>O</NER>
            <Speaker>PER0</Speaker>
          </token>
          <token id="5">
            <word>like</word>
            <lemma>like</lemma>
            <CharacterOffsetBegin>136</CharacterOffsetBegin>
            <CharacterOffsetEnd>140</CharacterOffsetEnd>
            <POS>VB</POS>
            <NER>O</NER>
            <Speaker>PER0</Speaker>
          </token>
          <token id="6">
            <word>me</word>
            <lemma>I</lemma>
            <CharacterOffsetBegin>141</CharacterOffsetBegin>
            <CharacterOffsetEnd>143</CharacterOffsetEnd>
            <POS>PRP</POS>
            <NER>O</NER>
            <Speaker>PER0</Speaker>
          </token>
          <token id="7">
            <word>.</word>
            <lemma>.</lemma>
            <CharacterOffsetBegin>143</CharacterOffsetBegin>
            <CharacterOffsetEnd>144</CharacterOffsetEnd>
            <POS>.</POS>
            <NER>O</NER>
            <Speaker>PER0</Speaker>
          </token>
        </tokens>
        <parse>(ROOT (S (NP (DT This) (NN one)) (VP (VBD did) (RB n't) (VP (VB like) (NP (PRP me)))) (. .))) </parse>
        <dependencies type="basic-dependencies">
          <dep type="root">
            <governor idx="0">ROOT</governor>
            <dependent idx="5">like</dependent>
          </dep>
          <dep type="det">
            <governor idx="2">one</governor>
            <dependent idx="1">This</dependent>
          </dep>
          <dep type="nsubj">
            <governor idx="5">like</governor>
            <dependent idx="2">one</dependent>
          </dep>
          <dep type="aux">
            <governor idx="5">like</governor>
            <dependent idx="3">did</dependent>
          </dep>
          <dep type="neg">
            <governor idx="5">like</governor>
            <dependent idx="4">n't</dependent>
          </dep>
          <dep type="dobj">
            <governor idx="5">like</governor>
            <dependent idx="6">me</dependent>
          </dep>
        </dependencies>
        <dependencies type="collapsed-dependencies">
          <dep type="root">
            <governor idx="0">ROOT</governor>
            <dependent idx="5">like</dependent>
          </dep>
          <dep type="det">
            <governor idx="2">one</governor>
            <dependent idx="1">This</dependent>
          </dep>
          <dep type="nsubj">
            <governor idx="5">like</governor>
            <dependent idx="2">one</dependent>
          </dep>
          <dep type="aux">
            <governor idx="5">like</governor>
            <dependent idx="3">did</dependent>
          </dep>
          <dep type="neg">
            <governor idx="5">like</governor>
            <dependent idx="4">n't</dependent>
          </dep>
          <dep type="dobj">
            <governor idx="5">like</governor>
            <dependent idx="6">me</dependent>
          </dep>
        </dependencies>
        <dependencies type="collapsed-ccprocessed-dependencies">
          <dep type="root">
            <governor idx="0">ROOT</governor>
            <dependent idx="5">like</dependent>
          </dep>
          <dep type="det">
            <governor idx="2">one</governor>
            <dependent idx="1">This</dependent>
          </dep>
          <dep type="nsubj">
            <governor idx="5">like</governor>
            <dependent idx="2">one</dependent>
          </dep>
          <dep type="aux">
            <governor idx="5">like</governor>
            <dependent idx="3">did</dependent>
          </dep>
          <dep type="neg">
            <governor idx="5">like</governor>
            <dependent idx="4">n't</dependent>
          </dep>
          <dep type="dobj">
            <governor idx="5">like</governor>
            <dependent idx="6">me</dependent>
          </dep>
        </dependencies>
      </sentence>
    </sentences>
    <coreference>
      <coreference>
        <mention representative="true">
          <sentence>1</sentence>
          <start>8</start>
          <end>9</end>
          <head>8</head>
          <text>they</text>
        </mention>
        <mention>
          <sentence>1</sentence>
          <start>14</start>
          <end>15</end>
          <head>14</head>
          <text>they</text>
        </mention>
      </coreference>
      <coreference>
        <mention representative="true">
          <sentence>1</sentence>
          <start>12</start>
          <end>13</end>
          <head>12</head>
          <text>me</text>
        </mention>
        <mention>
          <sentence>3</sentence>
          <start>6</start>
          <end>7</end>
          <head>6</head>
          <text>me</text>
        </mention>
      </coreference>
    </coreference>
  </document>
</root>
