<?xml version="1.0" encoding="UTF-8"?>
<?xml-stylesheet href="CoreNLP-to-HTML.xsl" type="text/xsl"?>
<root>
  <document>
    <sentences>
      <sentence id="1">
        <tokens>
          <token id="1">
            <word>Look</word>
            <lemma>look</lemma>
            <CharacterOffsetBegin>0</CharacterOffsetBegin>
            <CharacterOffsetEnd>4</CharacterOffsetEnd>
            <POS>VB</POS>
            <NER>O</NER>
            <Speaker>PER0</Speaker>
          </token>
          <token id="2">
            <word>,</word>
            <lemma>,</lemma>
            <CharacterOffsetBegin>4</CharacterOffsetBegin>
            <CharacterOffsetEnd>5</CharacterOffsetEnd>
            <POS>,</POS>
            <NER>O</NER>
            <Speaker>PER0</Speaker>
          </token>
          <token id="3">
            <word>we</word>
            <lemma>we</lemma>
            <CharacterOffsetBegin>6</CharacterOffsetBegin>
            <CharacterOffsetEnd>8</CharacterOffsetEnd>
            <POS>PRP</POS>
            <NER>O</NER>
            <Speaker>PER0</Speaker>
          </token>
          <token id="4">
            <word>'ve</word>
            <lemma>have</lemma>
            <CharacterOffsetBegin>8</CharacterOffsetBegin>
            <CharacterOffsetEnd>11</CharacterOffsetEnd>
            <POS>VBP</POS>
            <NER>O</NER>
            <Speaker>PER0</Speaker>
          </token>
          <token id="5">
            <word>got</word>
            <lemma>get</lemma>
            <CharacterOffsetBegin>12</CharacterOffsetBegin>
            <CharacterOffsetEnd>15</CharacterOffsetEnd>
            <POS>VBN</POS>
            <NER>O</NER>
            <Speaker>PER0</Speaker>
          </token>
          <token id="6">
            <word>to</word>
            <lemma>to</lemma>
            <CharacterOffsetBegin>16</CharacterOffsetBegin>
            <CharacterOffsetEnd>18</CharacterOffsetEnd>
            <POS>TO</POS>
            <NER>O</NER>
            <Speaker>PER0</Speaker>
          </token>
          <token id="7">
            <word>be</word>
            <lemma>be</lemma>
            <CharacterOffsetBegin>19</CharacterOffsetBegin>
            <CharacterOffsetEnd>21</CharacterOffsetEnd>
            <POS>VB</POS>
            <NER>O</NER>
            <Speaker>PER0</Speaker>
          </token>
          <token id="8">
            <word>tough</word>
            <lemma>tough</lemma>
            <CharacterOffsetBegin>22</CharacterOffsetBegin>
            <CharacterOffsetEnd>27</CharacterOffsetEnd>
            <POS>JJ</POS>
            <NER>O</NER>
            <Speaker>PER0</Speaker>
          </token>
          <token id="9">
            <word>.</word>
            <lemma>.</lemma>
            <CharacterOffsetBegin>27</CharacterOffsetBegin>
            <CharacterOffsetEnd>28</CharacterOffsetEnd>
            <POS>.</POS>
            <NER>O</NER>
            <Speaker>PER0</Speaker>
          </token>
        </tokens>
        <parse>(ROOT (S (S (VP (VB Look))) (, ,) (NP (PRP we)) (VP (VBP 've) (VP (VBN got) (S (VP (TO to) (VP (VB be) (ADJP (JJ tough))))))) (. .))) </parse>
        <dependencies type="basic-dependencies">
          <dep type="root">
            <governor idx="0">ROOT</governor>
            <dependent idx="5">got</dependent>
          </dep>
          <dep type="ccomp">
            <governor idx="5">got</governor>
            <dependent idx="1">Look</dependent>
          </dep>
          <dep type="nsubj">
            <governor idx="5">got</governor>
            <dependent idx="3">we</dependent>
          </dep>
          <dep type="aux">
            <governor idx="5">got</governor>
            <dependent idx="4">'ve</dependent>
          </dep>
          <dep type="aux">
            <governor idx="8">tough</governor>
            <dependent idx="6">to</dependent>
          </dep>
          <dep type="cop">
            <governor idx="8">tough</governor>
            <dependent idx="7">be</dependent>
          </dep>
          <dep type="xcomp">
            <governor idx="5">got</governor>
            <dependent idx="8">tough</dependent>
          </dep>
        </dependencies>
        <dependencies type="collapsed-dependencies">
          <dep type="root">
            <governor idx="0">ROOT</governor>
            <dependent idx="5">got</dependent>
          </dep>
          <dep type="ccomp">
            <governor idx="5">got</governor>
            <dependent idx="1">Look</dependent>
          </dep>
          <dep type="nsubj">
            <governor idx="5">got</governor>
            <dependent idx="3">we</dependent>
          </dep>
          <dep type="aux">
            <governor idx="5">got</governor>
            <dependent idx="4">'ve</dependent>
          </dep>
          <dep type="aux">
            <governor idx="8">tough</governor>
            <dependent idx="6">to</dependent>
          </dep>
          <dep type="cop">
            <governor idx="8">tough</governor>
            <dependent idx="7">be</dependent>
          </dep>
          <dep type="xcomp">
            <governor idx="5">got</governor>
            <dependent idx="8">tough</dependent>
          </dep>
        </dependencies>
        <dependencies type="collapsed-ccprocessed-dependencies">
          <dep type="root">
            <governor idx="0">ROOT</governor>
            <dependent idx="5">got</dependent>
          </dep>
          <dep type="ccomp">
            <governor idx="5">got</governor>
            <dependent idx="1">Look</dependent>
          </dep>
          <dep type="nsubj">
            <governor idx="5">got</governor>
            <dependent idx="3">we</dependent>
          </dep>
          <dep type="aux">
            <governor idx="5">got</governor>
            <dependent idx="4">'ve</dependent>
          </dep>
          <dep type="aux">
            <governor idx="8">tough</governor>
            <dependent idx="6">to</dependent>
          </dep>
          <dep type="cop">
            <governor idx="8">tough</governor>
            <dependent idx="7">be</dependent>
          </dep>
          <dep type="xcomp">
            <governor idx="5">got</governor>
            <dependent idx="8">tough</dependent>
          </dep>
        </dependencies>
      </sentence>
      <sentence id="2">
        <tokens>
          <token id="1">
            <word>We</word>
            <lemma>we</lemma>
            <CharacterOffsetBegin>29</CharacterOffsetBegin>
            <CharacterOffsetEnd>31</CharacterOffsetEnd>
            <POS>PRP</POS>
            <NER>O</NER>
            <Speaker>PER0</Speaker>
          </token>
          <token id="2">
            <word>'ve</word>
            <lemma>have</lemma>
            <CharacterOffsetBegin>31</CharacterOffsetBegin>
            <CharacterOffsetEnd>34</CharacterOffsetEnd>
            <POS>VBP</POS>
            <NER>O</NER>
            <Speaker>PER0</Speaker>
          </token>
          <token id="3">
            <word>got</word>
            <lemma>get</lemma>
            <CharacterOffsetBegin>35</CharacterOffsetBegin>
            <CharacterOffsetEnd>38</CharacterOffsetEnd>
            <POS>VBN</POS>
            <NER>O</NER>
            <Speaker>PER0</Speaker>
          </token>
          <token id="4">
            <word>to</word>
            <lemma>to</lemma>
            <CharacterOffsetBegin>39</CharacterOffsetBegin>
            <CharacterOffsetEnd>41</CharacterOffsetEnd>
            <POS>TO</POS>
            <NER>O</NER>
            <Speaker>PER0</Speaker>
          </token>
          <token id="5">
            <word>be</word>
            <lemma>be</lemma>
            <CharacterOffsetBegin>42</CharacterOffsetBegin>
            <CharacterOffsetEnd>44</CharacterOffsetEnd>
            <POS>VB</POS>
            <NER>O</NER>
            <Speaker>PER0</Speaker>
          </token>
          <token id="6">
            <word>smart</word>
            <lemma>smart</lemma>
            <CharacterOffsetBegin>45</CharacterOffsetBegin>
            <CharacterOffsetEnd>50</CharacterOffsetEnd>
            <POS>JJ</POS>
            <NER>O</NER>
            <Speaker>PER0</Speaker>
          </token>
          <token id="7">
            <word>.</word>
            <lemma>.</lemma>
            <CharacterOffsetBegin>50</CharacterOffsetBegin>
            <CharacterOffsetEnd>51</CharacterOffsetEnd>
            <POS>.</POS>
            <NER>O</NER>
            <Speaker>PER0</Speaker>
          </token>
        </tokens>
        <parse>(ROOT (S (NP (PRP We)) (VP (VBP 've) (VP (VBN got) (S (VP (TO to) (VP (VB be) (ADJP (JJ smart))))))) (. .))) </parse>
        <dependencies type="basic-dependencies">
          <dep type="root">
            <governor idx="0">ROOT</governor>
            <dependent idx="3">got</dependent>
          </dep>
          <dep type="nsubj">
            <governor idx="3">got</governor>
            <dependent idx="1">We</dependent>
          </dep>
          <dep type="aux">
            <governor idx="3">got</governor>
            <dependent idx="2">'ve</dependent>
          </dep>
          <dep type="aux">
            <governor idx="6">smart</governor>
            <dependent idx="4">to</dependent>
          </dep>
          <dep type="cop">
            <governor idx="6">smart</governor>
            <dependent idx="5">be</dependent>
          </dep>
          <dep type="xcomp">
            <governor idx="3">got</governor>
            <dependent idx="6">smart</dependent>
          </dep>
        </dependencies>
        <dependencies type="collapsed-dependencies">
          <dep type="root">
            <governor idx="0">ROOT</governor>
            <dependent idx="3">got</dependent>
          </dep>
          <dep type="nsubj">
            <governor idx="3">got</governor>
            <dependent idx="1">We</dependent>
          </dep>
          <dep type="aux">
            <governor idx="3">got</governor>
            <dependent idx="2">'ve</dependent>
          </dep>
          <dep type="aux">
            <governor idx="6">smart</governor>
            <dependent idx="4">to</dependent>
          </dep>
          <dep type="cop">
            <governor idx="6">smart</governor>
            <dependent idx="5">be</dependent>
          </dep>
          <dep type="xcomp">
            <governor idx="3">got</governor>
            <dependent idx="6">smart</dependent>
          </dep>
        </dependencies>
        <dependencies type="collapsed-ccprocessed-dependencies">
          <dep type="root">
            <governor idx="0">ROOT</governor>
            <dependent idx="3">got</dependent>
          </dep>
          <dep type="nsubj">
            <governor idx="3">got</governor>
            <dependent idx="1">We</dependent>
          </dep>
          <dep type="aux">
            <governor idx="3">got</governor>
            <dependent idx="2">'ve</dependent>
          </dep>
          <dep type="aux">
            <governor idx="6">smart</governor>
            <dependent idx="4">to</dependent>
          </dep>
          <dep type="cop">
            <governor idx="6">smart</governor>
            <dependent idx="5">be</dependent>
          </dep>
          <dep type="xcomp">
            <governor idx="3">got</governor>
            <dependent idx="6">smart</dependent>
          </dep>
        </dependencies>
      </sentence>
      <sentence id="3">
        <tokens>
          <token id="1">
            <word>We</word>
            <lemma>we</lemma>
            <CharacterOffsetBegin>52</CharacterOffsetBegin>
            <CharacterOffsetEnd>54</CharacterOffsetEnd>
            <POS>PRP</POS>
            <NER>O</NER>
            <Speaker>PER0</Speaker>
          </token>
          <token id="2">
            <word>'ve</word>
            <lemma>have</lemma>
            <CharacterOffsetBegin>54</CharacterOffsetBegin>
            <CharacterOffsetEnd>57</CharacterOffsetEnd>
            <POS>VBP</POS>
            <NER>O</NER>
            <Speaker>PER0</Speaker>
          </token>
          <token id="3">
            <word>got</word>
            <lemma>get</lemma>
            <CharacterOffsetBegin>58</CharacterOffsetBegin>
            <CharacterOffsetEnd>61</CharacterOffsetEnd>
            <POS>VBN</POS>
            <NER>O</NER>
            <Speaker>PER0</Speaker>
          </token>
          <token id="4">
            <word>to</word>
            <lemma>to</lemma>
            <CharacterOffsetBegin>62</CharacterOffsetBegin>
            <CharacterOffsetEnd>64</CharacterOffsetEnd>
            <POS>TO</POS>
            <NER>O</NER>
            <Speaker>PER0</Speaker>
          </token>
          <token id="5">
            <word>have</word>
            <lemma>have</lemma>
            <CharacterOffsetBegin>65</CharacterOffsetBegin>
            <CharacterOffsetEnd>69</CharacterOffsetEnd>
            <POS>VB</POS>
            <NER>O</NER>
            <Speaker>PER0</Speaker>
          </token>
          <token id="6">
            <word>heart</word>
            <lemma>heart</lemma>
            <CharacterOffsetBegin>70</CharacterOffsetBegin>
            <CharacterOffsetEnd>75</CharacterOffsetEnd>
            <POS>NN</POS>
            <NER>O</NER>
            <Speaker>PER0</Speaker>
          </token>
          <token id="7">
            <word>too</word>
            <lemma>too</lemma>
            <CharacterOffsetBegin>76</CharacterOffsetBegin>
            <CharacterOffsetEnd>79</CharacterOffsetEnd>
            <POS>RB</POS>
            <NER>O</NER>
            <Speaker>PER0</Speaker>
          </token>
          <token id="8">
            <word>.</word>
            <lemma>.</lemma>
            <CharacterOffsetBegin>79</CharacterOffsetBegin>
            <CharacterOffsetEnd>80</CharacterOffsetEnd>
            <POS>.</POS>
            <NER>O</NER>
            <Speaker>PER0</Speaker>
          </token>
        </tokens>
        <parse>(ROOT (S (NP (PRP We)) (VP (VBP 've) (VP (VBN got) (S (VP (TO to) (VP (VB have) (NP (NN heart)) (ADVP (RB too))))))) (. .))) </parse>
        <dependencies type="basic-dependencies">
          <dep type="root">
            <governor idx="0">ROOT</governor>
            <dependent idx="3">got</dependent>
          </dep>
          <dep type="nsubj">
            <governor idx="3">got</governor>
            <dependent idx="1">We</dependent>
          </dep>
          <dep type="aux">
            <governor idx="3">got</governor>
            <dependent idx="2">'ve</dependent>
          </dep>
          <dep type="aux">
            <governor idx="5">have</governor>
            <dependent idx="4">to</dependent>
          </dep>
          <dep type="xcomp">
            <governor idx="3">got</governor>
            <dependent idx="5">have</dependent>
          </dep>
          <dep type="dobj">
            <governor idx="5">have</governor>
            <dependent idx="6">heart</dependent>
          </dep>
          <dep type="advmod">
            <governor idx="5">have</governor>
            <dependent idx="7">too</dependent>
          </dep>
        </dependencies>
        <dependencies type="collapsed-dependencies">
          <dep type="root">
            <governor idx="0">ROOT</governor>
            <dependent idx="3">got</dependent>
          </dep>
          <dep type="nsubj">
            <governor idx="3">got</governor>
            <dependent idx="1">We</dependent>
          </dep>
          <dep type="aux">
            <governor idx="3">got</governor>
            <dependent idx="2">'ve</dependent>
          </dep>
          <dep type="aux">
            <governor idx="5">have</governor>
            <dependent idx="4">to</dependent>
          </dep>
          <dep type="xcomp">
            <governor idx="3">got</governor>
            <dependent idx="5">have</dependent>
          </dep>
          <dep type="dobj">
            <governor idx="5">have</governor>
            <dependent idx="6">heart</dependent>
          </dep>
          <dep type="advmod">
            <governor idx="5">have</governor>
            <dependent idx="7">too</dependent>
          </dep>
        </dependencies>
        <dependencies type="collapsed-ccprocessed-dependencies">
          <dep type="root">
            <governor idx="0">ROOT</governor>
            <dependent idx="3">got</dependent>
          </dep>
          <dep type="nsubj">
            <governor idx="3">got</governor>
            <dependent idx="1">We</dependent>
          </dep>
          <dep type="aux">
            <governor idx="3">got</governor>
            <dependent idx="2">'ve</dependent>
          </dep>
          <dep type="aux">
            <governor idx="5">have</governor>
            <dependent idx="4">to</dependent>
          </dep>
          <dep type="xcomp">
            <governor idx="3">got</governor>
            <dependent idx="5">have</dependent>
          </dep>
          <dep type="dobj">
            <governor idx="5">have</governor>
            <dependent idx="6">heart</dependent>
          </dep>
          <dep type="advmod">
            <governor idx="5">have</governor>
            <dependent idx="7">too</dependent>
          </dep>
        </dependencies>
      </sentence>
      <sentence id="4">
        <tokens>
          <token id="1">
            <word>We</word>
            <lemma>we</lemma>
            <CharacterOffsetBegin>81</CharacterOffsetBegin>
            <CharacterOffsetEnd>83</CharacterOffsetEnd>
            <POS>PRP</POS>
            <NER>O</NER>
            <Speaker>PER0</Speaker>
          </token>
          <token id="2">
            <word>'ve</word>
            <lemma>have</lemma>
            <CharacterOffsetBegin>83</CharacterOffsetBegin>
            <CharacterOffsetEnd>86</CharacterOffsetEnd>
            <POS>VBP</POS>
            <NER>O</NER>
            <Speaker>PER0</Speaker>
          </token>
          <token id="3">
            <word>got</word>
            <lemma>get</lemma>
            <CharacterOffsetBegin>87</CharacterOffsetBegin>
            <CharacterOffsetEnd>90</CharacterOffsetEnd>
            <POS>VBN</POS>
            <NER>O</NER>
            <Speaker>PER0</Speaker>
          </token>
          <token id="4">
            <word>to</word>
            <lemma>to</lemma>
            <CharacterOffsetBegin>91</CharacterOffsetBegin>
            <CharacterOffsetEnd>93</CharacterOffsetEnd>
            <POS>TO</POS>
            <NER>O</NER>
            <Speaker>PER0</Speaker>
          </token>
          <token id="5">
            <word>have</word>
            <lemma>have</lemma>
            <CharacterOffsetBegin>94</CharacterOffsetBegin>
            <CharacterOffsetEnd>98</CharacterOffsetEnd>
            <POS>VB</POS>
            <NER>O</NER>
            <Speaker>PER0</Speaker>
          </token>
          <token id="6">
            <word>heart</word>
            <lemma>heart</lemma>
            <CharacterOffsetBegin>99</CharacterOffsetBegin>
            <CharacterOffsetEnd>104</CharacterOffsetEnd>
            <POS>NN</POS>
            <NER>O</NER>
            <Speaker>PER0</Speaker>
          </token>
          <token id="7">
            <word>.</word>
            <lemma>.</lemma>
            <CharacterOffsetBegin>104</CharacterOffsetBegin>
            <CharacterOffsetEnd>105</CharacterOffsetEnd>
            <POS>.</POS>
            <NER>O</NER>
            <Speaker>PER0</Speaker>
          </token>
        </tokens>
        <parse>(ROOT (S (NP (PRP We)) (VP (VBP 've) (VP (VBN got) (S (VP (TO to) (VP (VB have) (NP (NN heart))))))) (. .))) </parse>
        <dependencies type="basic-dependencies">
          <dep type="root">
            <governor idx="0">ROOT</governor>
            <dependent idx="3">got</dependent>
          </dep>
          <dep type="nsubj">
            <governor idx="3">got</governor>
            <dependent idx="1">We</dependent>
          </dep>
          <dep type="aux">
            <governor idx="3">got</governor>
            <dependent idx="2">'ve</dependent>
          </dep>
          <dep type="aux">
            <governor idx="5">have</governor>
            <dependent idx="4">to</dependent>
          </dep>
          <dep type="xcomp">
            <governor idx="3">got</governor>
            <dependent idx="5">have</dependent>
          </dep>
          <dep type="dobj">
            <governor idx="5">have</governor>
            <dependent idx="6">heart</dependent>
          </dep>
        </dependencies>
        <dependencies type="collapsed-dependencies">
          <dep type="root">
            <governor idx="0">ROOT</governor>
            <dependent idx="3">got</dependent>
          </dep>
          <dep type="nsubj">
            <governor idx="3">got</governor>
            <dependent idx="1">We</dependent>
          </dep>
          <dep type="aux">
            <governor idx="3">got</governor>
            <dependent idx="2">'ve</dependent>
          </dep>
          <dep type="aux">
            <governor idx="5">have</governor>
            <dependent idx="4">to</dependent>
          </dep>
          <dep type="xcomp">
            <governor idx="3">got</governor>
            <dependent idx="5">have</dependent>
          </dep>
          <dep type="dobj">
            <governor idx="5">have</governor>
            <dependent idx="6">heart</dependent>
          </dep>
        </dependencies>
        <dependencies type="collapsed-ccprocessed-dependencies">
          <dep type="root">
            <governor idx="0">ROOT</governor>
            <dependent idx="3">got</dependent>
          </dep>
          <dep type="nsubj">
            <governor idx="3">got</governor>
            <dependent idx="1">We</dependent>
          </dep>
          <dep type="aux">
            <governor idx="3">got</governor>
            <dependent idx="2">'ve</dependent>
          </dep>
          <dep type="aux">
            <governor idx="5">have</governor>
            <dependent idx="4">to</dependent>
          </dep>
          <dep type="xcomp">
            <governor idx="3">got</governor>
            <dependent idx="5">have</dependent>
          </dep>
          <dep type="dobj">
            <governor idx="5">have</governor>
            <dependent idx="6">heart</dependent>
          </dep>
        </dependencies>
      </sentence>
      <sentence id="5">
        <tokens>
          <token id="1">
            <word>We</word>
            <lemma>we</lemma>
            <CharacterOffsetBegin>106</CharacterOffsetBegin>
            <CharacterOffsetEnd>108</CharacterOffsetEnd>
            <POS>PRP</POS>
            <NER>O</NER>
            <Speaker>PER0</Speaker>
          </token>
          <token id="2">
            <word>'ve</word>
            <lemma>have</lemma>
            <CharacterOffsetBegin>108</CharacterOffsetBegin>
            <CharacterOffsetEnd>111</CharacterOffsetEnd>
            <POS>VBP</POS>
            <NER>O</NER>
            <Speaker>PER0</Speaker>
          </token>
          <token id="3">
            <word>got</word>
            <lemma>get</lemma>
            <CharacterOffsetBegin>112</CharacterOffsetBegin>
            <CharacterOffsetEnd>115</CharacterOffsetEnd>
            <POS>VBN</POS>
            <NER>O</NER>
            <Speaker>PER0</Speaker>
          </token>
          <token id="4">
            <word>to</word>
            <lemma>to</lemma>
            <CharacterOffsetBegin>116</CharacterOffsetBegin>
            <CharacterOffsetEnd>118</CharacterOffsetEnd>
            <POS>TO</POS>
            <NER>O</NER>
            <Speaker>PER0</Speaker>
          </token>
          <token id="5">
            <word>take</word>
            <lemma>take</lemma>
            <CharacterOffsetBegin>119</CharacterOffsetBegin>
            <CharacterOffsetEnd>123</CharacterOffsetEnd>
            <POS>VB</POS>
            <NER>O</NER>
            <Speaker>PER0</Speaker>
          </token>
          <token id="6">
            <word>care</word>
            <lemma>care</lemma>
            <CharacterOffsetBegin>124</CharacterOffsetBegin>
            <CharacterOffsetEnd>128</CharacterOffsetEnd>
            <POS>NN</POS>
            <NER>O</NER>
            <Speaker>PER0</Speaker>
          </token>
          <token id="7">
            <word>of</word>
            <lemma>of</lemma>
            <CharacterOffsetBegin>129</CharacterOffsetBegin>
            <CharacterOffsetEnd>131</CharacterOffsetEnd>
            <POS>IN</POS>
            <NER>O</NER>
            <Speaker>PER0</Speaker>
          </token>
          <token id="8">
            <word>people</word>
            <lemma>people</lemma>
            <CharacterOffsetBegin>132</CharacterOffsetBegin>
            <CharacterOffsetEnd>138</CharacterOffsetEnd>
            <POS>NNS</POS>
            <NER>O</NER>
            <Speaker>PER0</Speaker>
          </token>
          <token id="9">
            <word>.</word>
            <lemma>.</lemma>
            <CharacterOffsetBegin>138</CharacterOffsetBegin>
            <CharacterOffsetEnd>139</CharacterOffsetEnd>
            <POS>.</POS>
            <NER>O</NER>
            <Speaker>PER0</Speaker>
          </token>
        </tokens>
        <parse>(ROOT (S (NP (PRP We)) (VP (VBP 've) (VP (VBN got) (S (VP (TO to) (VP (VB take) (NP (NP (NN care)) (PP (IN of) (NP (NNS people))))))))) (. .))) </parse>
        <dependencies type="basic-dependencies">
          <dep type="root">
            <governor idx="0">ROOT</governor>
            <dependent idx="3">got</dependent>
          </dep>
          <dep type="nsubj">
            <governor idx="3">got</governor>
            <dependent idx="1">We</dependent>
          </dep>
          <dep type="aux">
            <governor idx="3">got</governor>
            <dependent idx="2">'ve</dependent>
          </dep>
          <dep type="aux">
            <governor idx="5">take</governor>
            <dependent idx="4">to</dependent>
          </dep>
          <dep type="xcomp">
            <governor idx="3">got</governor>
            <dependent idx="5">take</dependent>
          </dep>
          <dep type="dobj">
            <governor idx="5">take</governor>
            <dependent idx="6">care</dependent>
          </dep>
          <dep type="prep">
            <governor idx="6">care</governor>
            <dependent idx="7">of</dependent>
          </dep>
          <dep type="pobj">
            <governor idx="7">of</governor>
            <dependent idx="8">people</dependent>
          </dep>
        </dependencies>
        <dependencies type="collapsed-dependencies">
          <dep type="root">
            <governor idx="0">ROOT</governor>
            <dependent idx="3">got</dependent>
          </dep>
          <dep type="nsubj">
            <governor idx="3">got</governor>
            <dependent idx="1">We</dependent>
          </dep>
          <dep type="aux">
            <governor idx="3">got</governor>
            <dependent idx="2">'ve</dependent>
          </dep>
          <dep type="aux">
            <governor idx="5">take</governor>
            <dependent idx="4">to</dependent>
          </dep>
          <dep type="xcomp">
            <governor idx="3">got</governor>
            <dependent idx="5">take</dependent>
          </dep>
          <dep type="dobj">
            <governor idx="5">take</governor>
            <dependent idx="6">care</dependent>
          </dep>
          <dep type="prep_of">
            <governor idx="6">care</governor>
            <dependent idx="8">people</dependent>
          </dep>
        </dependencies>
        <dependencies type="collapsed-ccprocessed-dependencies">
          <dep type="root">
            <governor idx="0">ROOT</governor>
            <dependent idx="3">got</dependent>
          </dep>
          <dep type="nsubj">
            <governor idx="3">got</governor>
            <dependent idx="1">We</dependent>
          </dep>
          <dep type="aux">
            <governor idx="3">got</governor>
            <dependent idx="2">'ve</dependent>
          </dep>
          <dep type="aux">
            <governor idx="5">take</governor>
            <dependent idx="4">to</dependent>
          </dep>
          <dep type="xcomp">
            <governor idx="3">got</governor>
            <dependent idx="5">take</dependent>
          </dep>
          <dep type="dobj">
            <governor idx="5">take</governor>
            <dependent idx="6">care</dependent>
          </dep>
          <dep type="prep_of">
            <governor idx="6">care</governor>
            <dependent idx="8">people</dependent>
          </dep>
        </dependencies>
      </sentence>
    </sentences>
    <coreference>
      <coreference>
        <mention representative="true">
          <sentence>1</sentence>
          <start>3</start>
          <end>4</end>
          <head>3</head>
          <text>we</text>
        </mention>
        <mention>
          <sentence>2</sentence>
          <start>1</start>
          <end>2</end>
          <head>1</head>
          <text>We</text>
        </mention>
        <mention>
          <sentence>3</sentence>
          <start>1</start>
          <end>2</end>
          <head>1</head>
          <text>We</text>
        </mention>
        <mention>
          <sentence>4</sentence>
          <start>1</start>
          <end>2</end>
          <head>1</head>
          <text>We</text>
        </mention>
        <mention>
          <sentence>5</sentence>
          <start>1</start>
          <end>2</end>
          <head>1</head>
          <text>We</text>
        </mention>
      </coreference>
    </coreference>
  </document>
</root>
